cpscripts/__init__.py
cpscripts/cellpose_predict.py
cpscripts-1.0.1.dist-info/METADATA
cpscripts-1.0.1.dist-info/WHEEL
cpscripts-1.0.1.dist-info/entry_points.txt
cpscripts-1.0.1.dist-info/top_level.txt
cpscripts-1.0.1.dist-info/RECORD
