Metadata-Version: 2.1
Name: cpscripts
Version: 1.0.1
Summary: Python cellpose.
Home-page: https://git.embl.de/grp-cba/embryo-3D-chromatin-tracing-workflow/-/tree/main/code/python/py-cellpose
Author: Arif Khan
Author-email: arif.khan@embl.com
License: MIT
Keywords: cellpose python package
Classifier: Programming Language :: Python :: 3
Classifier: License :: OSI Approved :: MIT License
Classifier: Operating System :: OS Independent
